aiopstack/__init__.py
aiopstack/app.py
aiopstack/cli.py
aiopstack/streamlit_helper.py
aiopstack/graphs/__init__.py
aiopstack/graphs/mcp/__init__.py
aiopstack/graphs/mcp/nodes.py
aiopstack/pages/ __init__.py
aiopstack/pages/home.py
aiopstack/pages/mcp.py
aiopstack/pages/settings.py
aiopstack/static/ __init__.py
aiopstack/static/mcp.png
aiopstack-0.1.1.dist-info/licenses/LICENSE
aiopstack-0.1.1.dist-info/METADATA
aiopstack-0.1.1.dist-info/WHEEL
aiopstack-0.1.1.dist-info/entry_points.txt
aiopstack-0.1.1.dist-info/top_level.txt
aiopstack-0.1.1.dist-info/RECORD
