Metadata-Version: 2.4
Name: aiopstack
Version: 0.1.1
Summary: A collection of AI Operational Agents built with Langchain/LangGraph and Streamlit-based GUI for real-time user interaction and visualization
Author-email: LaoXue AIOps <gibsonxue@gmail.com>
License-Expression: Apache-2.0
Project-URL: Homepage, https://github.com/hyperaiops/aiopstack.git
Project-URL: Issues, https://github.com/hyperaiops/aiopstack/issues
Classifier: Programming Language :: Python :: 3
Classifier: Intended Audience :: Developers
Classifier: Topic :: Software Development :: Build Tools
Requires-Python: <=3.13,>=3.9
License-File: LICENSE
Requires-Dist: streamlit
Requires-Dist: streamlit-authenticator
Requires-Dist: streamlit-local-storage
Requires-Dist: langgraph
Requires-Dist: langchain-openai
Requires-Dist: langchain-core
Requires-Dist: langchain_community
Requires-Dist: langchain-azure-ai
Requires-Dist: azure-identity
Requires-Dist: mcp
Requires-Dist: langchain_mcp_adapters
Dynamic: license-file
